{
  "id": "components/input",
  "title": "Input",
  "description": "Text input field with cursor, selection, word movement (Alt+←→), clipboard support, and optional multiline/wrapping.",
  "source": "@site/docs/components/input.mdx",
  "sourceDirName": "components",
  "slug": "/components/input",
  "permalink": "/teaui/docs/components/input",
  "draft": false,
  "unlisted": false,
  "editUrl": "https://github.com/colinta/teaui/tree/main/apps/docs/docs/components/input.mdx",
  "tags": [],
  "version": "current",
  "sidebarPosition": 3,
  "frontMatter": {
    "sidebar_position": 3,
    "title": "Input"
  },
  "sidebar": "docsSidebar",
  "previous": {
    "title": "Checkbox",
    "permalink": "/teaui/docs/components/checkbox"
  },
  "next": {
    "title": "Slider",
    "permalink": "/teaui/docs/components/slider"
  }
}